hedgehog/__init__.py
hedgehog/platform/__init__.py
hedgehog_platform-0.2.0.dist-info/DESCRIPTION.rst
hedgehog_platform-0.2.0.dist-info/METADATA
hedgehog_platform-0.2.0.dist-info/RECORD
hedgehog_platform-0.2.0.dist-info/WHEEL
hedgehog_platform-0.2.0.dist-info/entry_points.txt
hedgehog_platform-0.2.0.dist-info/metadata.json
hedgehog_platform-0.2.0.dist-info/top_level.txt
