Metadata-Version: 2.0
Name: hedgehog-platform
Version: 0.2.0
Summary: Hedgehog Platform abstractions
Home-page: https://github.com/PRIArobotics/HedgehogPlatform
Author: Clemens Koza
Author-email: koza@pria.at
License: AGPLv3+
Keywords: hedgehog robotics controller
Platform: UNKNOWN
Classifier: Development Status :: 4 - Beta
Classifier: Intended Audience :: Developers
Classifier: Topic :: Software Development
Classifier: License :: OSI Approved :: GNU Affero General Public License v3 or later (AGPLv3+)
Classifier: Programming Language :: Python :: 3
Provides-Extra: raspberry
Requires-Dist: RPi.GPIO; extra == 'raspberry'
Requires-Dist: pyserial; extra == 'raspberry'
